deskaone_requests/__init__.py
deskaone_requests/Client/__init__.py
deskaone_requests/Exceptions/__init__.py
deskaone_requests/Firebase/__init__.py
deskaone_requests/GAuth/__init__.py
deskaone_requests/Requests/__init__.py
deskaone_requests/Requests/browsers.json
deskaone_requests/Requests/Captcha.py
deskaone_requests/Requests/Cloud.py
deskaone_requests/Requests/Exceptions.py
deskaone_requests/Requests/Interpreters.py
deskaone_requests/Requests/User_Agent.py
deskaone_requests/Utils/__init__.py
deskaone_requests/Utils/AWSViker.py
deskaone_requests/Utils/Color.py
deskaone_requests/Utils/Crypto.py
deskaone_requests/Utils/Database.py
deskaone_requests/Utils/ProgressBar.py
deskaone_requests/Utils/ProxySearch.py
deskaone_requests/Utils/Random.py
deskaone_requests/Utils/Reset.py
deskaone_requests/Utils/Reverse.py
deskaone_requests/Utils/Timer.py
deskaone_requests/Utils/Typer.py
deskaone_requests/Utils/UserAgent.py
deskaone_requests-0.0.7.dist-info/WHEEL
deskaone_requests-0.0.7.dist-info/METADATA
deskaone_requests-0.0.7.dist-info/RECORD
